[
	{
		"id": 1,
		"title": "pexels-adrienn",
		"image": "/src/assets/images/gallery/fotografia-1.jpg",
		"alt": "fotografia-restaurante"
	},
	{
		"id": 2,
		"title": "pexels-annija-mieze",
		"image": "/src/assets/images/gallery/fotografia-2.jpg",
		"alt": "cheesecake-maracuya"
	},
	{
		"id": 3,
		"title": "pexels-enginakyurt",
		"image": "/src/assets/images/gallery/fotografia-3.jpg",
		"alt": "preparacion-platillos"
	},
	{
		"id": 4,
		"title": "pexels-fariphotography",
		"image": "/src/assets/images/gallery/fotografia-4.jpg",
		"alt": "gifiti"
	},
	{
		"id": 5,
		"title": "pexels-narda-yescas",
		"image": "/src/assets/images/gallery/fotografia-5.jpeg",
		"alt": "combos-especiales"
	},
	{
		"id": 6,
		"title": "pexels-pixabay",
		"image": "/src/assets/images/gallery/fotografia-6.jpg",
		"alt": "reunion-clientes"
	},
	{
		"id": 7,
		"title": "pexels-rachel-claire",
		"image": "/src/assets/images/gallery/fotografia-7.jpg",
		"alt": "torrejas-en-miel"
	},
	{
		"id": 8,
		"title": "pexels-vlah",
		"image": "/src/assets/images/gallery/fotografia-8.jpg",
		"alt": "restaurante"
	},
	{
		"id": 9,
		"title": "pexels-wildlittlethingsphoto",
		"image": "/src/assets/images/gallery/fotografia-9.jpg",
		"alt": "evento-boda"
	}
]
